comfy_3d_viewers/__init__.py
comfy_3d_viewers/web/assets/studio.exr
comfy_3d_viewers/web/html/viewer.html
comfy_3d_viewers/web/html/viewer_bvh.html
comfy_3d_viewers/web/html/viewer_cad_analysis.html
comfy_3d_viewers/web/html/viewer_cad_curve.html
comfy_3d_viewers/web/html/viewer_cad_edge.html
comfy_3d_viewers/web/html/viewer_cad_edge_detail.html
comfy_3d_viewers/web/html/viewer_cad_edge_vtk.html
comfy_3d_viewers/web/html/viewer_cad_hierarchy.html
comfy_3d_viewers/web/html/viewer_cad_occ.html
comfy_3d_viewers/web/html/viewer_cad_roi.html
comfy_3d_viewers/web/html/viewer_cad_spline.html
comfy_3d_viewers/web/html/viewer_compare_smpl_bvh.html
comfy_3d_viewers/web/html/viewer_dual.html
comfy_3d_viewers/web/html/viewer_dual_slider.html
comfy_3d_viewers/web/html/viewer_dual_textured.html
comfy_3d_viewers/web/html/viewer_fbx.html
comfy_3d_viewers/web/html/viewer_fbx_animation.html
comfy_3d_viewers/web/html/viewer_fbx_compare.html
comfy_3d_viewers/web/html/viewer_fbx_debug.html
comfy_3d_viewers/web/html/viewer_gaussian.html
comfy_3d_viewers/web/html/viewer_multi.html
comfy_3d_viewers/web/html/viewer_pbr.html
comfy_3d_viewers/web/html/viewer_uv.html
comfy_3d_viewers/web/html/viewer_vtk.html
comfy_3d_viewers/web/html/viewer_vtk_textured.html
comfy_3d_viewers/web/js/gsplat-bundle.js
comfy_3d_viewers/web/js/viewer-bundle.js
comfy_3d_viewers/web/js/vtk-gltf.js
comfy_3d_viewers/web/js/nodes/bbox_preview_vtk.js
comfy_3d_viewers/web/js/nodes/bvh_viewer.js
comfy_3d_viewers/web/js/nodes/cad_analysis_viewer.js
comfy_3d_viewers/web/js/nodes/cad_curve_plotter.js
comfy_3d_viewers/web/js/nodes/cad_edge_analysis.js
comfy_3d_viewers/web/js/nodes/cad_edge_detail_viewer.js
comfy_3d_viewers/web/js/nodes/cad_edge_viewer.js
comfy_3d_viewers/web/js/nodes/cad_edge_viewer_vtk.js
comfy_3d_viewers/web/js/nodes/cad_face_analysis.js
comfy_3d_viewers/web/js/nodes/cad_hierarchy_viewer.js
comfy_3d_viewers/web/js/nodes/cad_preview_batch.js
comfy_3d_viewers/web/js/nodes/cad_preview_occ.js
comfy_3d_viewers-0.2.2.dist-info/METADATA
comfy_3d_viewers-0.2.2.dist-info/WHEEL
comfy_3d_viewers-0.2.2.dist-info/RECORD
