Metadata-Version: 2.4
Name: comfy-3d-viewers
Version: 0.2.2
Summary: Reusable 3D viewer infrastructure for ComfyUI nodes
Project-URL: Homepage, https://github.com/PozzettiAndrea/comfy-3d-viewers
Project-URL: Repository, https://github.com/PozzettiAndrea/comfy-3d-viewers
Author: ComfyUI-GeometryPack Contributors
License-Expression: GPL-3.0-or-later
Keywords: 3d,comfyui,gaussian-splatting,mesh-visualization,viewer,vtk
Classifier: Development Status :: 4 - Beta
Classifier: Intended Audience :: Developers
Classifier: License :: OSI Approved :: GNU General Public License v3 or later (GPLv3+)
Classifier: Programming Language :: Python :: 3
Classifier: Programming Language :: Python :: 3.10
Classifier: Programming Language :: Python :: 3.11
Classifier: Programming Language :: Python :: 3.12
Classifier: Topic :: Multimedia :: Graphics :: 3D Modeling
Classifier: Topic :: Scientific/Engineering :: Visualization
Requires-Python: >=3.10
